auspex/__init__.py
auspex/config.py
auspex/data_format.py
auspex/experiment.py
auspex/log.py
auspex/parameter.py
auspex/refine.py
auspex/stream.py
auspex/sweep.py
auspex/analysis/CR_fits.py
auspex/analysis/__init__.py
auspex/analysis/fits.py
auspex/analysis/helpers.py
auspex/analysis/qubit_fits.py
auspex/analysis/resonator_fits.py
auspex/analysis/signal_analysis.py
auspex/filters/__init__.py
auspex/filters/average.py
auspex/filters/channelizer.py
auspex/filters/correlator.py
auspex/filters/debug.py
auspex/filters/elementwise.py
auspex/filters/filter.py
auspex/filters/framer.py
auspex/filters/integrator.py
auspex/filters/io.py
auspex/filters/plot.py
auspex/filters/singleshot.py
auspex/filters/stream_selectors.py
auspex/instruments/X6.py
auspex/instruments/__init__.py
auspex/instruments/agilent.py
auspex/instruments/alazar.py
auspex/instruments/ami.py
auspex/instruments/aps3.py
auspex/instruments/bbn.py
auspex/instruments/binutils.py
auspex/instruments/bnc.py
auspex/instruments/dsinstruments.py
auspex/instruments/hall_probe.py
auspex/instruments/holzworth.py
auspex/instruments/instrument.py
auspex/instruments/interface.py
auspex/instruments/keithley.py
auspex/instruments/kepco.py
auspex/instruments/keysight.py
auspex/instruments/lakeshore.py
auspex/instruments/lecroy.py
auspex/instruments/magnet.py
auspex/instruments/minicircuits.py
auspex/instruments/picosecond.py
auspex/instruments/prologix.py
auspex/instruments/rfmd.py
auspex/instruments/stanford.py
auspex/instruments/tektronix.py
auspex/instruments/utils.py
auspex/instruments/vaunix.py
auspex/instruments/yokogawa.py
auspex/qubit/__init__.py
auspex/qubit/mixer_calibration.py
auspex/qubit/pipeline.py
auspex/qubit/pulse_calibration.py
auspex/qubit/qubit_exp.py
auspex/qubit/single_shot_fidelity.py
auspex-2020.1.dist-info/LICENSE
auspex-2020.1.dist-info/METADATA
auspex-2020.1.dist-info/WHEEL
auspex-2020.1.dist-info/top_level.txt
auspex-2020.1.dist-info/RECORD
