Metadata-Version: 2.1
Name: auspex
Version: 2020.1
Summary: Scientific measurement platform specifically geared towards superconducting qubit measurements.
Home-page: https://github.com/BBN-Q/auspex
Author: Auspex Developers
License: Apache 2.0 License
Download-URL: https://github.com/BBN-Q/auspex
Keywords: quantum qubit pipeline measure instrument experiment control automate plot
Platform: UNKNOWN
Classifier: Development Status :: 4 - Beta
Classifier: Intended Audience :: Science/Research
Classifier: License :: OSI Approved :: Apache Software License
Classifier: Operating System :: MacOS
Classifier: Operating System :: POSIX
Classifier: Programming Language :: Python :: 3 :: Only
Classifier: Programming Language :: Python :: 3.6
Classifier: Programming Language :: Python :: 3.7
Classifier: Topic :: Scientific/Engineering
Requires-Python: >=3.6
Requires-Dist: bbndb (>=2020.1)
Requires-Dist: numpy (>=1.11.1)
Requires-Dist: scipy (>=0.17.1)
Requires-Dist: PyVISA (>=1.8)
Requires-Dist: pandas (>=0.18.1)
Requires-Dist: networkx (>=1.11)
Requires-Dist: matplotlib (>=2.0.0)
Requires-Dist: psutil (>=5.0.0)
Requires-Dist: cffi (>=1.11.5)
Requires-Dist: scikit-learn (>=0.19.1)
Requires-Dist: pyzmq (>=16.0.0)
Requires-Dist: pyusb (>=1.0.2)
Requires-Dist: python-usbtmc (>=0.8)
Requires-Dist: ipykernel (>=5.0.0)
Requires-Dist: ipywidgets (>=7.0.0)
Requires-Dist: sqlalchemy (>=1.2.15)
Requires-Dist: pyserial (>=3.4)
Requires-Dist: setproctitle
Requires-Dist: progress
Requires-Dist: PyVISA-Py (>=0.3)
